whoisjson/__init__.py
whoisjson-0.2.0.dist-info/licenses/LICENSE
whoisjson-0.2.0.dist-info/METADATA
whoisjson-0.2.0.dist-info/WHEEL
whoisjson-0.2.0.dist-info/top_level.txt
whoisjson-0.2.0.dist-info/RECORD
